cppref/__init__.py
cppref/conf.py
cppref/core/__init__.py
cppref/core/cppreference/__init__.py
cppref/core/cppreference/cppreference.py
cppref/core/cppreference/description.py
cppref/core/cppreference/div.py
cppref/core/cppreference/table/__init__.py
cppref/core/cppreference/table/base.py
cppref/core/cppreference/table/t_dcl_begin.py
cppref/core/cppreference/table/t_dsc_begin.py
cppref/core/cppreference/table/t_general.py
cppref/core/cppreference/table/t_par_begin.py
cppref/core/cppreference/table/t_rev_begin.py
cppref/core/cppreference/table/t_sdsc_begin.py
cppref/core/cppreference/table/typing_.py
cppref/core/cppreference/table/width.py
cppref/core/cppreference/utils.py
cppref/core/processor.py
cppref/cppref.py
cppref/fzf.py
cppref/typing_.py
cppref/utils.py
cppref-0.1.3.dist-info/WHEEL
cppref-0.1.3.dist-info/entry_points.txt
cppref-0.1.3.dist-info/METADATA
cppref-0.1.3.dist-info/RECORD
