Metadata-Version: 2.3
Name: cppref
Version: 0.1.3
Summary: Refer to the cppreference with this cli!
Requires-Dist: fire>=0.7.1
Requires-Dist: lxml>=6.0.0
Requires-Dist: playwright>=1.55.0
Requires-Dist: toml>=0.10.2
Requires-Dist: tqdm>=4.67.1
Requires-Dist: types-lxml>=2025.3.30
Requires-Python: >=3.13
